LICENSE
LICENSE.3rdparty
README.rst
setup.py
pyfarm/__init__.py
pyfarm.master.egg-info/PKG-INFO
pyfarm.master.egg-info/SOURCES.txt
pyfarm.master.egg-info/dependency_links.txt
pyfarm.master.egg-info/entry_points.txt
pyfarm.master.egg-info/namespace_packages.txt
pyfarm.master.egg-info/requires.txt
pyfarm.master.egg-info/top_level.txt
pyfarm/master/__init__.py
pyfarm/master/application.py
pyfarm/master/config.py
pyfarm/master/entrypoints.py
pyfarm/master/index.py
pyfarm/master/initial.py
pyfarm/master/login.py
pyfarm/master/testutil.py
pyfarm/master/utility.py
pyfarm/master/api/__init__.py
pyfarm/master/api/agent_updates.py
pyfarm/master/api/agents.py
pyfarm/master/api/jobgroups.py
pyfarm/master/api/jobqueues.py
pyfarm/master/api/jobs.py
pyfarm/master/api/jobtypes.py
pyfarm/master/api/pathmaps.py
pyfarm/master/api/software.py
pyfarm/master/api/tags.py
pyfarm/master/api/tasklogs.py
pyfarm/master/etc/master.yml
pyfarm/master/static/favicon.ico
pyfarm/master/static/css/bootstrap-theme.css
pyfarm/master/static/css/bootstrap-theme.css.map
pyfarm/master/static/css/bootstrap-theme.min.css
pyfarm/master/static/css/bootstrap-tree.css
pyfarm/master/static/css/bootstrap.css
pyfarm/master/static/css/bootstrap.css.map
pyfarm/master/static/css/bootstrap.min.css
pyfarm/master/static/css/headings.css
pyfarm/master/static/css/index.css
pyfarm/master/static/css/job.css
pyfarm/master/static/css/jobs.css
pyfarm/master/static/css/jobtype.css
pyfarm/master/static/css/layout.css
pyfarm/master/static/css/login.css
pyfarm/master/static/css/setup.css
pyfarm/master/static/fonts/glyphicons-halflings-regular.eot
pyfarm/master/static/fonts/glyphicons-halflings-regular.svg
pyfarm/master/static/fonts/glyphicons-halflings-regular.woff
pyfarm/master/static/fonts/glyphicons-halflings-regular.woff2
pyfarm/master/static/js/agent.js
pyfarm/master/static/js/agents.js
pyfarm/master/static/js/bootstrap-tree.js
pyfarm/master/static/js/jobs.js
pyfarm/master/static/js/jobtype.js
pyfarm/master/static/js/layout.js
pyfarm/master/static/js/vendor/bootstrap.js
pyfarm/master/static/js/vendor/bootstrap.min.js
pyfarm/master/static/js/vendor/canop-tzdetect-2b2feb6811.js
pyfarm/master/static/js/vendor/jquery-2.0.3.min.js
pyfarm/master/static/js/vendor/moment-2.8.3.min.js
