Metadata-Version: 1.1
Name: pyfarm.master
Version: 0.8.6
Summary: Sub-library which contains the code necessary to communicate with the database via a REST api.
Home-page: https://github.com/pyfarm/pyfarm-master
Author: Oliver Palmer
Author-email: development@pyfarm.net
License: Apache v2.0
Platform: UNKNOWN
Classifier: Development Status :: 3 - Alpha
Classifier: Environment :: Other Environment
Classifier: Intended Audience :: Developers
Classifier: License :: OSI Approved :: Apache Software License
Classifier: Natural Language :: English
Classifier: Operating System :: OS Independent
Classifier: Programming Language :: Python :: 2.7
Classifier: Programming Language :: Python :: 3.3
Classifier: Programming Language :: Python :: 3.4
Classifier: Topic :: System :: Distributed Computing
